sypter/__init__.py
sypter/__main__.py
sypter-0.0.3.dist-info/LICENSE
sypter-0.0.3.dist-info/METADATA
sypter-0.0.3.dist-info/WHEEL
sypter-0.0.3.dist-info/entry_points.txt
sypter-0.0.3.dist-info/top_level.txt
sypter-0.0.3.dist-info/RECORD
