Metadata-Version: 2.1
Name: sypter
Version: 0.0.3
Summary: Frontend testing framework
Author-email: Temur Chichua <contact@temurchichua.com>
License: GNU GENERAL PUBLIC LICENSE
Project-URL: Homepage, https://github.com/temurchichua/sypter
Project-URL: GitHub, https://github.com/temurchichua/sypter
Keywords: frontend,testing,freamwork
Classifier: License :: OSI Approved :: MIT License
Classifier: Programming Language :: Python
Classifier: Programming Language :: Python :: 3
Requires-Python: >=3.9
License-File: LICENSE
Requires-Dist: selenium
Requires-Dist: geckodriver-autoinstaller
Provides-Extra: dev
Requires-Dist: black ; extra == 'dev'
Requires-Dist: bumpver ; extra == 'dev'
Requires-Dist: isort ; extra == 'dev'
Requires-Dist: pip-tools ; extra == 'dev'
Requires-Dist: pytest ; extra == 'dev'
Requires-Dist: tox ; extra == 'dev'
Requires-Dist: twine ; extra == 'dev'
